{"nodes":[{"label":"Data Scientist","x":-119.31077575683594,"y":1730.029296875,"id":"16","attributes":{"Modularity Class":"2","Degree":"1"},"color":"rgb(255,95,3)","size":10.0},{"label":"Behavior Analytics","x":350.8070373535156,"y":3230.708740234375,"id":"20","attributes":{"Modularity Class":"2","Degree":"1"},"color":"rgb(255,95,3)","size":10.0},{"label":"Neural Network","x":-308.6030578613281,"y":1911.5831298828125,"id":"15","attributes":{"Modularity Class":"2","Degree":"1"},"color":"rgb(255,95,3)","size":10.0},{"label":"Intellectual Property","x":-1684.1209716796875,"y":-616.0902099609375,"id":"68","attributes":{"Modularity Class":"8","Degree":"1"},"color":"rgb(129,49,43)","size":10.0},{"label":"Fundraising","x":-862.8248901367188,"y":-2850.645751953125,"id":"78","attributes":{"Modularity Class":"0","Degree":"1"},"color":"rgb(255,59,92)","size":10.0},{"label":"Customers","x":140.51771545410156,"y":-384.6627502441406,"id":"3","attributes":{"Modularity Class":"8","Degree":"3"},"color":"rgb(129,49,43)","size":13.333333969116211},{"label":"Design","x":1577.48974609375,"y":-16.182512283325195,"id":"4","attributes":{"Modularity Class":"4","Degree":"9"},"color":"rgb(232,95,178)","size":23.33333396911621},{"label":"Private Investor","x":-679.1017456054688,"y":-3046.64990234375,"id":"77","attributes":{"Modularity Class":"0","Degree":"1"},"color":"rgb(255,59,92)","size":10.0},{"label":"Conversion Rate","x":1007.93408203125,"y":-3067.13330078125,"id":"63","attributes":{"Modularity Class":"7","Degree":"1"},"color":"rgb(76,137,178)","size":10.0},{"label":"Branding Consultnat","x":2057.051513671875,"y":-68.04743957519531,"id":"29","attributes":{"Modularity Class":"4","Degree":"1"},"color":"rgb(232,95,178)","size":10.0},{"label":"Collaboration Tools","x":-1011.3023681640625,"y":282.2015686035156,"id":"8","attributes":{"Modularity Class":"8","Degree":"5"},"color":"rgb(129,49,43)","size":16.666667938232422},{"label":"React Native","x":-4414.744140625,"y":-947.8089599609375,"id":"54","attributes":{"Modularity Class":"6","Degree":"1"},"color":"rgb(210,134,134)","size":10.0},{"label":"Seed Capital","x":-339.9723815917969,"y":-3032.21142578125,"id":"75","attributes":{"Modularity Class":"0","Degree":"1"},"color":"rgb(255,59,92)","size":10.0},{"label":"Machine Learning","x":389.7602844238281,"y":1443.649658203125,"id":"14","attributes":{"Modularity Class":"2","Degree":"1"},"color":"rgb(255,95,3)","size":10.0},{"label":"AI | Machine Learning","x":-101.06584167480469,"y":1217.544921875,"id":"0","attributes":{"Modularity Class":"2","Degree":"8"},"color":"rgb(255,95,3)","size":21.66666603088379},{"label":"Web3","x":-859.705078125,"y":-1563.0054931640625,"id":"10","attributes":{"Modularity Class":"1","Degree":"5"},"color":"rgb(224,125,123)","size":16.666667938232422},{"label":"Algorithms","x":-471.9462585449219,"y":1680.6732177734375,"id":"11","attributes":{"Modularity Class":"2","Degree":"1"},"color":"rgb(255,95,3)","size":10.0},{"label":"IT Security","x":-5166.45556640625,"y":199.35704040527344,"id":"47","attributes":{"Modularity Class":"5","Degree":"1"},"color":"rgb(157,134,0)","size":10.0},{"label":"Swift","x":-4424.57080078125,"y":-729.52099609375,"id":"55","attributes":{"Modularity Class":"6","Degree":"1"},"color":"rgb(210,134,134)","size":10.0},{"label":"Notion","x":-916.5980834960938,"y":735.1019897460938,"id":"70","attributes":{"Modularity Class":"8","Degree":"3"},"color":"rgb(129,49,43)","size":13.333333969116211},{"label":"Artificial Intelligence","x":109.66749572753906,"y":1872.370361328125,"id":"12","attributes":{"Modularity Class":"2","Degree":"1"},"color":"rgb(255,95,3)","size":10.0},{"label":"Web Development","x":-4591.46630859375,"y":305.1770324707031,"id":"41","attributes":{"Modularity Class":"5","Degree":"9"},"color":"rgb(157,134,0)","size":23.33333396911621},{"label":"UX Design","x":3588.65625,"y":607.6886596679688,"id":"36","attributes":{"Modularity Class":"4","Degree":"1"},"color":"rgb(232,95,178)","size":10.0},{"label":"B2B Marketing","x":779.475830078125,"y":-2848.519287109375,"id":"57","attributes":{"Modularity Class":"7","Degree":"1"},"color":"rgb(76,137,178)","size":10.0},{"label":"NFT","x":-1214.451416015625,"y":-1718.82763671875,"id":"82","attributes":{"Modularity Class":"1","Degree":"1"},"color":"rgb(224,125,123)","size":10.0},{"label":"Data Prediction","x":193.7595977783203,"y":2529.0712890625,"id":"17","attributes":{"Modularity Class":"2","Degree":"4"},"color":"rgb(255,95,3)","size":15.0},{"label":"Entrepreneurs","x":613.6399536132812,"y":-358.7887268066406,"id":"26","attributes":{"Modularity Class":"8","Degree":"1"},"color":"rgb(129,49,43)","size":10.0},{"label":"Venture Capital","x":-496.4469909667969,"y":-2842.2509765625,"id":"76","attributes":{"Modularity Class":"0","Degree":"1"},"color":"rgb(255,59,92)","size":10.0},{"label":"Angel Investor","x":-169.0388641357422,"y":-2753.189697265625,"id":"74","attributes":{"Modularity Class":"0","Degree":"1"},"color":"rgb(255,59,92)","size":10.0},{"label":"Software Development Main","x":-2783.868896484375,"y":-223.5418243408203,"id":"5","attributes":{"Modularity Class":"5","Degree":"4"},"color":"rgb(157,134,0)","size":15.0},{"label":"UI \u0026 UX Design","x":2957.793212890625,"y":577.7420654296875,"id":"34","attributes":{"Modularity Class":"4","Degree":"7"},"color":"rgb(232,95,178)","size":20.0},{"label":"Data Visualization","x":571.7103271484375,"y":3090.578125,"id":"19","attributes":{"Modularity Class":"2","Degree":"1"},"color":"rgb(255,95,3)","size":10.0},{"label":"Defi","x":-996.8577880859375,"y":-2134.28466796875,"id":"81","attributes":{"Modularity Class":"1","Degree":"1"},"color":"rgb(224,125,123)","size":10.0},{"label":"Lead Generation","x":1328.7427978515625,"y":-2709.149169921875,"id":"66","attributes":{"Modularity Class":"7","Degree":"1"},"color":"rgb(76,137,178)","size":10.0},{"label":"Email Marketing","x":1755.87353515625,"y":-2645.655029296875,"id":"65","attributes":{"Modularity Class":"7","Degree":"1"},"color":"rgb(76,137,178)","size":10.0},{"label":"Adwords","x":1641.5125732421875,"y":-2824.447021484375,"id":"56","attributes":{"Modularity Class":"7","Degree":"1"},"color":"rgb(76,137,178)","size":10.0},{"label":"Software Development","x":-3411.47021484375,"y":488.5406799316406,"id":"50","attributes":{"Modularity Class":"5","Degree":"3"},"color":"rgb(157,134,0)","size":13.333333969116211},{"label":"Brand Designer","x":2005.52197265625,"y":519.047607421875,"id":"30","attributes":{"Modularity Class":"4","Degree":"1"},"color":"rgb(232,95,178)","size":10.0},{"label":"Interaction Design","x":2052.0185546875,"y":-400.4406433105469,"id":"35","attributes":{"Modularity Class":"4","Degree":"1"},"color":"rgb(232,95,178)","size":10.0},{"label":"Content Marketing","x":1680.20458984375,"y":-2159.722900390625,"id":"58","attributes":{"Modularity Class":"7","Degree":"1"},"color":"rgb(76,137,178)","size":10.0},{"label":"Django","x":-4833.4794921875,"y":890.3290405273438,"id":"40","attributes":{"Modularity Class":"5","Degree":"1"},"color":"rgb(157,134,0)","size":10.0},{"label":"Venture Funding","x":-489.1169738769531,"y":-2270.9541015625,"id":"9","attributes":{"Modularity Class":"0","Degree":"6"},"color":"rgb(255,59,92)","size":18.333332061767578},{"label":"Discord Community","x":-2243.827880859375,"y":-1655.69775390625,"id":"22","attributes":{"Modularity Class":"3","Degree":"1"},"color":"rgb(76,132,103)","size":10.0},{"label":"Data Mining","x":328.9237976074219,"y":1707.515625,"id":"13","attributes":{"Modularity Class":"2","Degree":"1"},"color":"rgb(255,95,3)","size":10.0},{"label":"Graphic Design","x":2085.599609375,"y":302.8036804199219,"id":"28","attributes":{"Modularity Class":"4","Degree":"1"},"color":"rgb(232,95,178)","size":10.0},{"label":"Twilio","x":-5026.3701171875,"y":536.9385375976562,"id":"44","attributes":{"Modularity Class":"5","Degree":"1"},"color":"rgb(157,134,0)","size":10.0},{"label":"saas","x":-5399.2421875,"y":207.38743591308594,"id":"48","attributes":{"Modularity Class":"5","Degree":"1"},"color":"rgb(157,134,0)","size":10.0},{"label":"Redux","x":-5274.74169921875,"y":704.3976440429688,"id":"43","attributes":{"Modularity Class":"5","Degree":"1"},"color":"rgb(157,134,0)","size":10.0},{"label":"User Retention","x":-2370.005859375,"y":-1885.74169921875,"id":"25","attributes":{"Modularity Class":"3","Degree":"1"},"color":"rgb(76,132,103)","size":10.0},{"label":"Slack","x":-1526.324951171875,"y":548.1693115234375,"id":"71","attributes":{"Modularity Class":"8","Degree":"1"},"color":"rgb(129,49,43)","size":10.0},{"label":"Community Management","x":-1907.5902099609375,"y":-2264.735107421875,"id":"21","attributes":{"Modularity Class":"3","Degree":"1"},"color":"rgb(76,132,103)","size":10.0},{"label":"Blockchain","x":-1256.3035888671875,"y":-2040.8045654296875,"id":"79","attributes":{"Modularity Class":"1","Degree":"1"},"color":"rgb(224,125,123)","size":10.0},{"label":"Digital Marketing","x":1018.86181640625,"y":-2283.703125,"id":"6","attributes":{"Modularity Class":"7","Degree":"13"},"color":"rgb(76,137,178)","size":30.0},{"label":"PostgreSQL","x":-5082.63818359375,"y":867.2696533203125,"id":"42","attributes":{"Modularity Class":"5","Degree":"1"},"color":"rgb(157,134,0)","size":10.0},{"label":"Trello","x":-1398.5374755859375,"y":791.2274780273438,"id":"73","attributes":{"Modularity Class":"8","Degree":"1"},"color":"rgb(129,49,43)","size":10.0},{"label":"Visual design","x":2299.025390625,"y":-185.48915100097656,"id":"32","attributes":{"Modularity Class":"4","Degree":"1"},"color":"rgb(232,95,178)","size":10.0},{"label":"Websocket","x":-5130.365234375,"y":-75.59931945800781,"id":"46","attributes":{"Modularity Class":"5","Degree":"1"},"color":"rgb(157,134,0)","size":10.0},{"label":"DAPP","x":-694.31689453125,"y":-1913.133056640625,"id":"80","attributes":{"Modularity Class":"1","Degree":"1"},"color":"rgb(224,125,123)","size":10.0},{"label":"Product Market fit","x":-1186.801025390625,"y":-547.4061279296875,"id":"7","attributes":{"Modularity Class":"8","Degree":"3"},"color":"rgb(129,49,43)","size":13.333333969116211},{"label":"User Acquistion","x":-2200.1982421875,"y":-2046.6822509765625,"id":"24","attributes":{"Modularity Class":"3","Degree":"1"},"color":"rgb(76,132,103)","size":10.0},{"label":"Founders","x":430.4469299316406,"y":-7.086595058441162,"id":"27","attributes":{"Modularity Class":"8","Degree":"1"},"color":"rgb(129,49,43)","size":10.0},{"label":"UI Prototyping","x":3376.008544921875,"y":1102.9898681640625,"id":"39","attributes":{"Modularity Class":"4","Degree":"1"},"color":"rgb(232,95,178)","size":10.0},{"label":"Spaced","x":-471.7790222167969,"y":-717.1168212890625,"id":"1","attributes":{"Modularity Class":"8","Degree":"10"},"color":"rgb(129,49,43)","size":25.0},{"label":"Java","x":-3662.99609375,"y":1056.514892578125,"id":"51","attributes":{"Modularity Class":"5","Degree":"1"},"color":"rgb(157,134,0)","size":10.0},{"label":"Mobile Development","x":-3831.4580078125,"y":-707.476318359375,"id":"53","attributes":{"Modularity Class":"6","Degree":"4"},"color":"rgb(210,134,134)","size":15.0},{"label":"E-commerce","x":1426.52783203125,"y":-2027.5770263671875,"id":"64","attributes":{"Modularity Class":"7","Degree":"1"},"color":"rgb(76,137,178)","size":10.0},{"label":"Objective C","x":-4265.4765625,"y":-1179.9940185546875,"id":"52","attributes":{"Modularity Class":"6","Degree":"1"},"color":"rgb(210,134,134)","size":10.0},{"label":"UX Prototyping","x":3566.387451171875,"y":948.0646362304688,"id":"37","attributes":{"Modularity Class":"4","Degree":"1"},"color":"rgb(232,95,178)","size":10.0},{"label":"Social Media Marketing","x":1494.776123046875,"y":-2463.13720703125,"id":"61","attributes":{"Modularity Class":"7","Degree":"1"},"color":"rgb(76,137,178)","size":10.0},{"label":"SEO Specialist","x":1795.386474609375,"y":-2388.56396484375,"id":"62","attributes":{"Modularity Class":"7","Degree":"1"},"color":"rgb(76,137,178)","size":10.0},{"label":"Marketing Designer","x":2296.33935546875,"y":174.93077087402344,"id":"33","attributes":{"Modularity Class":"4","Degree":"1"},"color":"rgb(232,95,178)","size":10.0},{"label":"Android","x":-3866.024658203125,"y":838.6914672851562,"id":"49","attributes":{"Modularity Class":"5","Degree":"1"},"color":"rgb(157,134,0)","size":10.0},{"label":"3d Design","x":1739.495361328125,"y":509.2929382324219,"id":"31","attributes":{"Modularity Class":"4","Degree":"1"},"color":"rgb(232,95,178)","size":10.0},{"label":"UI Design","x":3726.81298828125,"y":735.9674682617188,"id":"38","attributes":{"Modularity Class":"4","Degree":"1"},"color":"rgb(232,95,178)","size":10.0},{"label":"Scalibilty","x":-1639.1014404296875,"y":-302.6931457519531,"id":"69","attributes":{"Modularity Class":"8","Degree":"1"},"color":"rgb(129,49,43)","size":10.0},{"label":"Community Building","x":-1689.7777099609375,"y":-1641.5955810546875,"id":"2","attributes":{"Modularity Class":"3","Degree":"8"},"color":"rgb(76,132,103)","size":21.66666603088379},{"label":"Mobile Marketing","x":1039.9744873046875,"y":-2768.875244140625,"id":"60","attributes":{"Modularity Class":"7","Degree":"1"},"color":"rgb(76,137,178)","size":10.0},{"label":"PPC Strategy","x":1475.235107421875,"y":-2990.79833984375,"id":"67","attributes":{"Modularity Class":"7","Degree":"1"},"color":"rgb(76,137,178)","size":10.0},{"label":"Influenece Marketing","x":1264.34765625,"y":-3068.126953125,"id":"59","attributes":{"Modularity Class":"7","Degree":"1"},"color":"rgb(76,137,178)","size":10.0},{"label":"Market Research","x":88.66896057128906,"y":3205.501220703125,"id":"18","attributes":{"Modularity Class":"2","Degree":"1"},"color":"rgb(255,95,3)","size":10.0},{"label":"Figma","x":-1155.30078125,"y":879.2093505859375,"id":"72","attributes":{"Modularity Class":"8","Degree":"1"},"color":"rgb(129,49,43)","size":10.0},{"label":"Community Moderator","x":-2169.61767578125,"y":-2264.058837890625,"id":"23","attributes":{"Modularity Class":"3","Degree":"1"},"color":"rgb(76,132,103)","size":10.0},{"label":"Typescript","x":-5377.9921875,"y":477.1661682128906,"id":"45","attributes":{"Modularity Class":"5","Degree":"1"},"color":"rgb(157,134,0)","size":10.0}],"edges":[{"source":"41","target":"5","id":"361","attributes":{},"color":"rgb(157,134,0)","size":1.0},{"source":"24","target":"2","id":"330","attributes":{},"color":"rgb(76,132,103)","size":1.0},{"source":"42","target":"41","id":"348","attributes":{},"color":"rgb(157,134,0)","size":1.0},{"source":"57","target":"6","id":"364","attributes":{},"color":"rgb(76,137,178)","size":1.0},{"source":"20","target":"17","id":"325","attributes":{},"color":"rgb(255,95,3)","size":1.0},{"source":"6","target":"1","id":"311","attributes":{},"color":"rgb(102,93,110)","size":1.0},{"source":"14","target":"0","id":"319","attributes":{},"color":"rgb(255,95,3)","size":1.0},{"source":"38","target":"34","id":"344","attributes":{},"color":"rgb(232,95,178)","size":1.0},{"source":"49","target":"50","id":"355","attributes":{},"color":"rgb(157,134,0)","size":1.0},{"source":"12","target":"0","id":"317","attributes":{},"color":"rgb(255,95,3)","size":1.0},{"source":"32","target":"4","id":"338","attributes":{},"color":"rgb(232,95,178)","size":1.0},{"source":"8","target":"1","id":"313","attributes":{},"color":"rgb(129,49,43)","size":1.0},{"source":"31","target":"4","id":"337","attributes":{},"color":"rgb(232,95,178)","size":1.0},{"source":"34","target":"4","id":"340","attributes":{},"color":"rgb(232,95,178)","size":1.0},{"source":"28","target":"4","id":"334","attributes":{},"color":"rgb(232,95,178)","size":1.0},{"source":"34","target":"34","id":"346","attributes":{},"color":"rgb(232,95,178)","size":1.0},{"source":"53","target":"5","id":"360","attributes":{},"color":"rgb(183,134,67)","size":1.0},{"source":"2","target":"1","id":"307","attributes":{},"color":"rgb(102,90,73)","size":1.0},{"source":"5","target":"1","id":"310","attributes":{},"color":"rgb(143,91,21)","size":1.0},{"source":"23","target":"2","id":"329","attributes":{},"color":"rgb(76,132,103)","size":1.0},{"source":"70","target":"70","id":"390","attributes":{},"color":"rgb(128,128,128)","size":1.0},{"source":"72","target":"8","id":"379","attributes":{},"color":"rgb(129,49,43)","size":1.0},{"source":"69","target":"7","id":"376","attributes":{},"color":"rgb(129,49,43)","size":1.0},{"source":"52","target":"53","id":"357","attributes":{},"color":"rgb(210,134,134)","size":1.0},{"source":"15","target":"0","id":"320","attributes":{},"color":"rgb(255,95,3)","size":1.0},{"source":"4","target":"1","id":"309","attributes":{},"color":"rgb(180,72,110)","size":1.0},{"source":"17","target":"0","id":"322","attributes":{},"color":"rgb(255,95,3)","size":1.0},{"source":"30","target":"4","id":"336","attributes":{},"color":"rgb(232,95,178)","size":1.0},{"source":"47","target":"41","id":"353","attributes":{},"color":"rgb(157,134,0)","size":1.0},{"source":"35","target":"4","id":"341","attributes":{},"color":"rgb(232,95,178)","size":1.0},{"source":"76","target":"9","id":"383","attributes":{},"color":"rgb(255,59,92)","size":1.0},{"source":"81","target":"10","id":"388","attributes":{},"color":"rgb(224,125,123)","size":1.0},{"source":"60","target":"6","id":"367","attributes":{},"color":"rgb(76,137,178)","size":1.0},{"source":"11","target":"0","id":"316","attributes":{},"color":"rgb(255,95,3)","size":1.0},{"source":"66","target":"6","id":"373","attributes":{},"color":"rgb(76,137,178)","size":1.0},{"source":"82","target":"10","id":"389","attributes":{},"color":"rgb(224,125,123)","size":1.0},{"source":"80","target":"10","id":"387","attributes":{},"color":"rgb(224,125,123)","size":1.0},{"source":"59","target":"6","id":"366","attributes":{},"color":"rgb(76,137,178)","size":1.0},{"source":"71","target":"8","id":"378","attributes":{},"color":"rgb(129,49,43)","size":1.0},{"source":"58","target":"6","id":"365","attributes":{},"color":"rgb(76,137,178)","size":1.0},{"source":"27","target":"3","id":"333","attributes":{},"color":"rgb(129,49,43)","size":1.0},{"source":"73","target":"8","id":"380","attributes":{},"color":"rgb(129,49,43)","size":1.0},{"source":"22","target":"2","id":"328","attributes":{},"color":"rgb(76,132,103)","size":1.0},{"source":"50","target":"5","id":"362","attributes":{},"color":"rgb(157,134,0)","size":1.0},{"source":"39","target":"34","id":"345","attributes":{},"color":"rgb(232,95,178)","size":1.0},{"source":"46","target":"41","id":"352","attributes":{},"color":"rgb(157,134,0)","size":1.0},{"source":"40","target":"41","id":"347","attributes":{},"color":"rgb(157,134,0)","size":1.0},{"source":"45","target":"41","id":"351","attributes":{},"color":"rgb(157,134,0)","size":1.0},{"source":"51","target":"50","id":"356","attributes":{},"color":"rgb(157,134,0)","size":1.0},{"source":"25","target":"2","id":"331","attributes":{},"color":"rgb(76,132,103)","size":1.0},{"source":"55","target":"53","id":"359","attributes":{},"color":"rgb(210,134,134)","size":1.0},{"source":"78","target":"9","id":"385","attributes":{},"color":"rgb(255,59,92)","size":1.0},{"source":"44","target":"41","id":"350","attributes":{},"color":"rgb(157,134,0)","size":1.0},{"source":"67","target":"6","id":"374","attributes":{},"color":"rgb(76,137,178)","size":1.0},{"source":"74","target":"9","id":"381","attributes":{},"color":"rgb(255,59,92)","size":1.0},{"source":"75","target":"9","id":"382","attributes":{},"color":"rgb(255,59,92)","size":1.0},{"source":"54","target":"53","id":"358","attributes":{},"color":"rgb(210,134,134)","size":1.0},{"source":"7","target":"1","id":"312","attributes":{},"color":"rgb(129,49,43)","size":1.0},{"source":"48","target":"41","id":"354","attributes":{},"color":"rgb(157,134,0)","size":1.0},{"source":"19","target":"17","id":"324","attributes":{},"color":"rgb(255,95,3)","size":1.0},{"source":"9","target":"1","id":"314","attributes":{},"color":"rgb(192,54,67)","size":1.0},{"source":"62","target":"6","id":"369","attributes":{},"color":"rgb(76,137,178)","size":1.0},{"source":"64","target":"6","id":"371","attributes":{},"color":"rgb(76,137,178)","size":1.0},{"source":"16","target":"0","id":"321","attributes":{},"color":"rgb(255,95,3)","size":1.0},{"source":"33","target":"4","id":"339","attributes":{},"color":"rgb(232,95,178)","size":1.0},{"source":"79","target":"10","id":"386","attributes":{},"color":"rgb(224,125,123)","size":1.0},{"source":"65","target":"6","id":"372","attributes":{},"color":"rgb(76,137,178)","size":1.0},{"source":"68","target":"7","id":"375","attributes":{},"color":"rgb(129,49,43)","size":1.0},{"source":"43","target":"41","id":"349","attributes":{},"color":"rgb(157,134,0)","size":1.0},{"source":"63","target":"6","id":"370","attributes":{},"color":"rgb(76,137,178)","size":1.0},{"source":"77","target":"9","id":"384","attributes":{},"color":"rgb(255,59,92)","size":1.0},{"source":"0","target":"1","id":"306","attributes":{},"color":"rgb(192,72,23)","size":1.0},{"source":"13","target":"0","id":"318","attributes":{},"color":"rgb(255,95,3)","size":1.0},{"source":"2","target":"2","id":"326","attributes":{},"color":"rgb(76,132,103)","size":1.0},{"source":"10","target":"1","id":"315","attributes":{},"color":"rgb(176,87,83)","size":1.0},{"source":"18","target":"17","id":"323","attributes":{},"color":"rgb(255,95,3)","size":1.0},{"source":"70","target":"8","id":"377","attributes":{},"color":"rgb(129,49,43)","size":1.0},{"source":"29","target":"4","id":"335","attributes":{},"color":"rgb(232,95,178)","size":1.0},{"source":"21","target":"2","id":"327","attributes":{},"color":"rgb(76,132,103)","size":1.0},{"source":"56","target":"6","id":"363","attributes":{},"color":"rgb(76,137,178)","size":1.0},{"source":"37","target":"34","id":"343","attributes":{},"color":"rgb(232,95,178)","size":1.0},{"source":"36","target":"34","id":"342","attributes":{},"color":"rgb(232,95,178)","size":1.0},{"source":"26","target":"3","id":"332","attributes":{},"color":"rgb(129,49,43)","size":1.0},{"source":"61","target":"6","id":"368","attributes":{},"color":"rgb(76,137,178)","size":1.0},{"source":"3","target":"1","id":"308","attributes":{},"color":"rgb(129,49,43)","size":1.0}]}